mysqlping/__init__.py
mysqlping/apps.py
mysqlping/middleware.py
django_mysqlping-0.1.1.dist-info/LICENSE
django_mysqlping-0.1.1.dist-info/METADATA
django_mysqlping-0.1.1.dist-info/WHEEL
django_mysqlping-0.1.1.dist-info/top_level.txt
django_mysqlping-0.1.1.dist-info/RECORD
