Metadata-Version: 2.1
Name: django-mysqlping
Version: 0.1.1
Summary: Ping to MySQL in Django middleware.
Home-page: https://github.com/tokibito/django-mysqlping
Author: Shinya Okano
Author-email: tokibito@gmail.com
License: UNKNOWN
Platform: UNKNOWN
Classifier: Development Status :: 5 - Production/Stable
Classifier: Framework :: Django
Classifier: Programming Language :: Python :: 3.5
Classifier: Programming Language :: Python :: 3.6
Classifier: Programming Language :: Python :: 3.7
Classifier: License :: OSI Approved :: MIT License
Requires-Dist: Django (>=1.11)
Provides-Extra: develop
Requires-Dist: pytest ; extra == 'develop'
Requires-Dist: flake8 ; extra == 'develop'
Requires-Dist: pytest-django ; extra == 'develop'
Requires-Dist: pytest-pythonpath ; extra == 'develop'
Requires-Dist: tox ; extra == 'develop'
Requires-Dist: wheel ; extra == 'develop'
Requires-Dist: twine ; extra == 'develop'
